qf/__init__.py
qf/__main__.py
quick_find_aaron_alphabet-1.0.1.dist-info/LICENSE
quick_find_aaron_alphabet-1.0.1.dist-info/METADATA
quick_find_aaron_alphabet-1.0.1.dist-info/WHEEL
quick_find_aaron_alphabet-1.0.1.dist-info/entry_points.txt
quick_find_aaron_alphabet-1.0.1.dist-info/top_level.txt
quick_find_aaron_alphabet-1.0.1.dist-info/RECORD
