Metadata-Version: 2.1
Name: quick-find-aaron-alphabet
Version: 1.0.1
Summary: quickly find
Author-email: Aaron Alphabet <aaron.alphabet@gmx.de>
License: Copyright © 2022 <Aaron Alphabet>
Classifier: License :: OSI Approved :: MIT License
Classifier: Programming Language :: Python :: 3
Requires-Python: >=3.10
License-File: LICENSE
